rust_sbml-0.7.0.dist-info/METADATA
rust_sbml-0.7.0.dist-info/WHEEL
rust_sbml.cpython-39-darwin.so
rust_sbml-0.7.0.dist-info/RECORD
