Metadata-Version: 2.1
Name: rust_sbml
Version: 0.7.0
Summary: A parser for SBML
Author: Jorge Carrasco Muriel <carrascomurielj@gmail.com>
Author-Email: Jorge Carrasco Muriel <carrascomurielj@gmail.com>
License: MIT OR Apache-2.0
